{"stats":{"minecraft:mined":{"minecraft:white_bed":3,"minecraft:cobblestone_stairs":3,"minecraft:brewing_stand":2,"minecraft:obsidian":65,"minecraft:granite":145,"minecraft:grass_block":840,"minecraft:crimson_fungus":1,"minecraft:hopper":7,"minecraft:oxeye_daisy":1,"minecraft:nether_wart":80,"minecraft:spawner":8,"minecraft:polished_blackstone_bricks":1,"minecraft:tall_seagrass":7,"minecraft:magma_block":83,"minecraft:iron_ore":1583,"minecraft:fire":53,"minecraft:pumpkin":8,"minecraft:deepslate_lapis_ore":16,"minecraft:pointed_dripstone":1,"minecraft:oak_stairs":7,"minecraft:birch_wall_sign":3,"minecraft:spruce_slab":1,"minecraft:deepslate_redstone_ore":73,"minecraft:brown_mushroom":8,"minecraft:red_bed":1,"minecraft:blackstone":476,"minecraft:torch":18,"minecraft:chest":9,"minecraft:glass":4,"minecraft:nether_quartz_ore":577,"minecraft:cobblestone":179,"minecraft:oak_planks":9,"minecraft:sugar_cane":684,"minecraft:wall_torch":96,"minecraft:seagrass":1,"minecraft:white_terracotta":1,"minecraft:repeater":9,"minecraft:warped_nylium":36,"minecraft:powered_rail":2,"minecraft:birch_log":658,"minecraft:wheat":829,"minecraft:warped_fungus":10,"minecraft:grass":385,"minecraft:oak_log":18,"minecraft:sand":277,"minecraft:dirt":477,"minecraft:ancient_debris":10,"minecraft:netherrack":5417,"minecraft:piston":5,"minecraft:oak_leaves":4,"minecraft:deepslate":521,"minecraft:nether_gold_ore":103,"minecraft:diamond_ore":50,"minecraft:tuff":76,"minecraft:deepslate_diamond_ore":35,"minecraft:oak_door":7,"minecraft:nether_bricks":4,"minecraft:lever":2,"minecraft:glow_lichen":2,"minecraft:ladder":1,"minecraft:spruce_fence":1,"minecraft:redstone_wire":15,"minecraft:birch_slab":1,"minecraft:red_mushroom":2,"minecraft:large_fern":1,"minecraft:redstone_ore":330,"minecraft:furnace":13,"minecraft:carrots":142,"minecraft:snow":1,"minecraft:andesite":204,"minecraft:peony":1,"minecraft:bookshelf":1,"minecraft:potatoes":1,"minecraft:deepslate_iron_ore":68,"minecraft:rail":4,"minecraft:warped_stem":1,"minecraft:stone":4064,"minecraft:birch_stairs":2,"minecraft:glass_pane":5,"minecraft:comparator":3,"minecraft:basalt":69,"minecraft:observer":11,"minecraft:dandelion":1,"minecraft:oak_fence":2,"minecraft:crafting_table":104,"minecraft:emerald_ore":14,"minecraft:warped_roots":3,"minecraft:rose_bush":4,"minecraft:lectern":160,"minecraft:copper_ore":61,"minecraft:tall_grass":8,"minecraft:deepslate_coal_ore":28,"minecraft:lapis_ore":41,"minecraft:deepslate_gold_ore":60,"minecraft:polished_blackstone_brick_stairs":2,"minecraft:diorite":152,"minecraft:warped_wart_block":2,"minecraft:birch_planks":59,"minecraft:redstone_torch":5,"minecraft:birch_leaves":16,"minecraft:yellow_bed":1,"minecraft:coal_ore":3409,"minecraft:sunflower":3,"minecraft:gravel":400,"minecraft:cobweb":26,"minecraft:stone_bricks":2,"minecraft:gold_ore":158,"minecraft:deepslate_emerald_ore":1,"minecraft:infested_stone":8,"minecraft:birch_fence":9},"minecraft:broken":{"minecraft:iron_shovel":3,"minecraft:diamond_helmet":1,"minecraft:iron_boots":1,"minecraft:stone_pickaxe":1,"minecraft:diamond_boots":1,"minecraft:stone_axe":3,"minecraft:iron_sword":1,"minecraft:stone_shovel":3,"minecraft:stone_sword":1,"minecraft:iron_axe":3,"minecraft:iron_pickaxe":22,"minecraft:iron_helmet":1},"minecraft:custom":{"minecraft:animals_bred":359,"minecraft:interact_with_crafting_table":494,"minecraft:leave_game":14,"minecraft:time_since_death":2135815,"minecraft:sprint_one_cm":6995290,"minecraft:damage_blocked_by_shield":5180,"minecraft:drop":364,"minecraft:talked_to_villager":362,"minecraft:play_time":2903183,"minecraft:deaths":2,"minecraft:jump":32247,"minecraft:interact_with_brewingstand":33,"minecraft:walk_on_water_one_cm":479296,"minecraft:enchant_item":27,"minecraft:interact_with_furnace":441,"minecraft:traded_with_villager":161,"minecraft:sleep_in_bed":76,"minecraft:open_enderchest":72,"minecraft:damage_dealt":169799,"minecraft:crouch_one_cm":78325,"minecraft:interact_with_smithing_table":9,"minecraft:inspect_dropper":23,"minecraft:interact_with_anvil":21,"minecraft:mob_kills":1191,"minecraft:inspect_hopper":148,"minecraft:climb_one_cm":86510,"minecraft:walk_one_cm":7412841,"minecraft:strider_one_cm":1216105,"minecraft:sneak_time":26588,"minecraft:walk_under_water_one_cm":332523,"minecraft:boat_one_cm":2773948,"minecraft:interact_with_blast_furnace":109,"minecraft:total_world_time":2903183,"minecraft:interact_with_grindstone":13,"minecraft:interact_with_stonecutter":5,"minecraft:time_since_rest":2853,"minecraft:damage_taken":14793,"minecraft:swim_one_cm":611565,"minecraft:fly_one_cm":5258750,"minecraft:open_chest":1803,"minecraft:fall_one_cm":706718,"minecraft:fish_caught":8},"minecraft:killed_by":{"minecraft:creeper":1},"minecraft:crafted":{"minecraft:grindstone":1,"minecraft:smooth_stone":3,"minecraft:oak_planks":48,"minecraft:blaze_powder":6,"minecraft:cooked_chicken":42,"minecraft:birch_boat":4,"minecraft:birch_slab":24,"minecraft:stone":320,"minecraft:lever":1,"minecraft:diamond_shovel":1,"minecraft:bookshelf":17,"minecraft:cooked_mutton":7,"minecraft:quartz_block":37,"minecraft:glass":233,"minecraft:hopper":71,"minecraft:repeater":2,"minecraft:diamond_helmet":2,"minecraft:diamond_leggings":1,"minecraft:bow":5,"minecraft:iron_boots":3,"minecraft:birch_fence_gate":5,"minecraft:comparator":1,"minecraft:chest":92,"minecraft:birch_door":9,"minecraft:rail":16,"minecraft:birch_button":1,"minecraft:ender_eye":3,"minecraft:glass_bottle":63,"minecraft:dropper":1,"minecraft:emerald":138,"minecraft:cooked_porkchop":110,"minecraft:diamond_axe":1,"minecraft:crafting_table":10,"minecraft:wooden_pickaxe":2,"minecraft:iron_helmet":7,"minecraft:chest_minecart":1,"minecraft:smithing_table":1,"minecraft:red_wool":3,"minecraft:copper_ingot":142,"minecraft:hopper_minecart":3,"minecraft:birch_planks":2336,"minecraft:lectern":1,"minecraft:iron_chestplate":3,"minecraft:book":266,"minecraft:paper":1056,"minecraft:diamond_pickaxe":3,"minecraft:shield":5,"minecraft:birch_fence":228,"minecraft:stick":908,"minecraft:stone_slab":6,"minecraft:iron_ingot":290,"minecraft:iron_pickaxe":26,"minecraft:iron_block":67,"minecraft:stone_sword":1,"minecraft:gold_ingot":110,"minecraft:redstone_torch":9,"minecraft:netherite_ingot":1,"minecraft:composter":1,"minecraft:birch_stairs":16,"minecraft:shears":1,"minecraft:golden_carrot":67,"minecraft:wooden_sword":1,"minecraft:coal":2326,"minecraft:redstone":117,"minecraft:stone_shovel":4,"minecraft:fishing_rod":4,"minecraft:furnace":9,"minecraft:blast_furnace":1,"minecraft:piston":5,"minecraft:bone_meal":174,"minecraft:stone_stairs":8,"minecraft:flint_and_steel":1,"minecraft:iron_axe":6,"minecraft:ladder":24,"minecraft:iron_hoe":5,"minecraft:stone_pickaxe":1,"minecraft:diamond_boots":2,"minecraft:redstone_block":171,"minecraft:minecart":2,"minecraft:birch_sign":6,"minecraft:observer":5,"minecraft:cooked_beef":203,"minecraft:sugar":1,"minecraft:coal_block":438,"minecraft:red_dye":6,"minecraft:netherite_pickaxe":1,"minecraft:diamond_sword":2,"minecraft:enchanting_table":1,"minecraft:powered_rail":6,"minecraft:iron_sword":11,"minecraft:red_bed":1,"minecraft:bucket":2,"minecraft:stone_axe":3,"minecraft:enchanted_book":23,"minecraft:bread":74,"minecraft:air":0,"minecraft:gold_nugget":630,"minecraft:warped_fungus_on_a_stick":4,"minecraft:fermented_spider_eye":1,"minecraft:wooden_axe":1,"minecraft:writable_book":135,"minecraft:iron_shovel":5,"minecraft:iron_leggings":5,"minecraft:stonecutter":1,"minecraft:anvil":1,"minecraft:white_bed":1,"minecraft:torch":1860,"minecraft:lapis_lazuli":27,"minecraft:lapis_block":37,"minecraft:diamond_chestplate":1,"minecraft:ender_chest":3},"minecraft:picked_up":{"minecraft:wooden_axe":1,"minecraft:wheat":804,"minecraft:diamond_sword":2,"minecraft:potion":2,"minecraft:enchanted_book":2,"minecraft:brewing_stand":2,"minecraft:polished_blackstone_brick_stairs":2,"minecraft:string":94,"minecraft:raw_copper":153,"minecraft:cooked_salmon":1,"minecraft:pufferfish":1,"minecraft:gold_nugget":639,"minecraft:cobbled_deepslate":392,"minecraft:comparator":3,"minecraft:rose_bush":3,"minecraft:redstone_torch":8,"minecraft:iron_pickaxe":1,"minecraft:coal_block":31,"minecraft:iron_boots":1,"minecraft:furnace":13,"minecraft:stick":45,"minecraft:music_disc_blocks":1,"minecraft:oak_fence":2,"minecraft:torch":180,"minecraft:porkchop":112,"minecraft:pointed_dripstone":2,"minecraft:diorite":117,"minecraft:rotten_flesh":221,"minecraft:white_terracotta":1,"minecraft:blaze_rod":22,"minecraft:obsidian":57,"minecraft:cod":6,"minecraft:cobblestone":3733,"minecraft:birch_log":658,"minecraft:magma_block":41,"minecraft:feather":168,"minecraft:cooked_beef":246,"minecraft:magma_cream":1,"minecraft:repeater":9,"minecraft:warped_fungus_on_a_stick":1,"minecraft:birch_slab":1,"minecraft:andesite":185,"minecraft:potato":2,"minecraft:flint":68,"minecraft:tuff":47,"minecraft:lapis_lazuli":460,"minecraft:dirt":1282,"minecraft:name_tag":1,"minecraft:bone":126,"minecraft:bow":5,"minecraft:wheat_seeds":2253,"minecraft:raw_gold":260,"minecraft:glowstone_dust":9,"minecraft:powered_rail":4,"minecraft:oak_planks":40,"minecraft:cooked_porkchop":5,"minecraft:warped_wart_block":2,"minecraft:sand":258,"minecraft:ink_sac":206,"minecraft:iron_hoe":1,"minecraft:sugar":2,"minecraft:diamond":145,"minecraft:lever":2,"minecraft:writable_book":4,"minecraft:crossbow":1,"minecraft:granite":110,"minecraft:emerald":16,"minecraft:netherrack":3152,"minecraft:diamond_pickaxe":1,"minecraft:crafting_table":104,"minecraft:ladder":1,"minecraft:chicken":75,"minecraft:nether_wart":99,"minecraft:brown_mushroom":7,"minecraft:shield":1,"minecraft:red_bed":1,"minecraft:iron_axe":1,"minecraft:wooden_sword":1,"minecraft:iron_shovel":1,"minecraft:birch_fence":9,"minecraft:blackstone":238,"minecraft:beef":217,"minecraft:observer":11,"minecraft:spruce_slab":2,"minecraft:minecart":4,"minecraft:lectern":160,"minecraft:sugar_cane":1129,"minecraft:chest":10,"minecraft:birch_sapling":49,"minecraft:piston":5,"minecraft:egg":909,"minecraft:raw_iron":2036,"minecraft:stone":11,"minecraft:oak_door":6,"minecraft:spruce_fence":1,"minecraft:trident":2,"minecraft:carrot":504,"minecraft:redstone":1958,"minecraft:arrow":132,"minecraft:peony":1,"minecraft:nether_bricks":4,"minecraft:glow_berries":3,"minecraft:mutton":1,"minecraft:rail":19,"minecraft:white_wool":10,"minecraft:oxeye_daisy":4,"minecraft:basalt":33,"minecraft:glow_ink_sac":8,"minecraft:salmon":2,"minecraft:leather":266,"minecraft:red_mushroom":2,"minecraft:birch_planks":60,"minecraft:crimson_fungus":1,"minecraft:oak_log":18,"minecraft:lily_pad":23,"minecraft:ancient_debris":10,"minecraft:gunpowder":63,"minecraft:cobblestone_stairs":3,"minecraft:white_banner":1,"minecraft:stone_bricks":2,"minecraft:kelp":3,"minecraft:warped_stem":1,"minecraft:iron_ingot":1,"minecraft:cooked_chicken":86,"minecraft:iron_sword":2,"minecraft:book":124,"minecraft:warped_fungus":10,"minecraft:birch_boat":60,"minecraft:pumpkin":8,"minecraft:quartz":553,"minecraft:dandelion":1,"minecraft:gravel":260,"minecraft:birch_stairs":2,"minecraft:white_bed":1,"minecraft:spider_eye":24,"minecraft:slime_ball":5,"minecraft:birch_sign":3,"minecraft:warped_roots":8,"minecraft:baked_potato":2,"minecraft:warped_nylium":5,"minecraft:coal":4544,"minecraft:hopper":9,"minecraft:ender_pearl":5},"minecraft:used":{"minecraft:iron_shovel":1007,"minecraft:ladder":13,"minecraft:shield":213,"minecraft:chest":28,"minecraft:iron_sword":1320,"minecraft:stone":197,"minecraft:zombie_spawn_egg":60,"minecraft:carrot":210,"minecraft:obsidian":22,"minecraft:milk_bucket":2,"minecraft:glass":106,"minecraft:lava_bucket":25,"minecraft:villager_spawn_egg":36,"minecraft:warped_nylium":1,"minecraft:hopper_minecart":3,"minecraft:repeater":10,"minecraft:bow":79,"minecraft:furnace":18,"minecraft:egg":628,"minecraft:diorite":1,"minecraft:warped_fungus_on_a_stick":451,"minecraft:dropper":1,"minecraft:stone_pickaxe":132,"minecraft:powered_rail":6,"minecraft:ender_pearl":1,"minecraft:wooden_pickaxe":16,"minecraft:composter":1,"minecraft:sugar_cane":133,"minecraft:diamond_axe":172,"minecraft:glow_berries":3,"minecraft:sand":1,"minecraft:blast_furnace":1,"minecraft:deepslate_lapis_ore":4,"minecraft:birch_fence":225,"minecraft:redstone_torch":10,"minecraft:lever":2,"minecraft:birch_fence_gate":5,"minecraft:birch_slab":1,"minecraft:bread":18,"minecraft:lectern":162,"minecraft:diamond_ore":8,"minecraft:gravel":17,"minecraft:diamond_sword":934,"minecraft:wooden_sword":47,"minecraft:grindstone":1,"minecraft:smithing_table":1,"minecraft:andesite":2,"minecraft:chest_minecart":1,"minecraft:bone_meal":131,"minecraft:trident":107,"minecraft:stone_sword":141,"minecraft:enchanting_table":1,"minecraft:flint_and_steel":2,"minecraft:redstone_ore":2,"minecraft:stone_shovel":398,"minecraft:redstone":25,"minecraft:ender_chest":2,"minecraft:cooked_salmon":4,"minecraft:cooked_chicken":5,"minecraft:netherrack":707,"minecraft:torch":1905,"minecraft:brewing_stand":2,"minecraft:dirt":709,"minecraft:anvil":1,"minecraft:hopper":18,"minecraft:stone_stairs":13,"minecraft:birch_door":5,"minecraft:iron_hoe":293,"minecraft:wooden_axe":28,"minecraft:bookshelf":16,"minecraft:iron_axe":815,"minecraft:polished_blackstone_brick_stairs":61,"minecraft:basalt":20,"minecraft:golden_carrot":17,"minecraft:beef":3,"minecraft:netherite_pickaxe":3408,"minecraft:cooked_beef":210,"minecraft:observer":16,"minecraft:golden_axe":4,"minecraft:cobbled_deepslate":7,"minecraft:wheat_seeds":987,"minecraft:cooked_mutton":7,"minecraft:water_bucket":271,"minecraft:cobblestone_stairs":67,"minecraft:birch_planks":239,"minecraft:glass_bottle":12,"minecraft:birch_boat":60,"minecraft:stonecutter":1,"minecraft:rail":8,"minecraft:comparator":4,"minecraft:crafting_table":108,"minecraft:birch_sign":5,"minecraft:red_bed":4,"minecraft:white_bed":2,"minecraft:oak_log":1,"minecraft:piston":10,"minecraft:diamond_pickaxe":8736,"minecraft:diamond_shovel":567,"minecraft:chicken":1,"minecraft:iron_pickaxe":5973,"minecraft:stone_axe":368,"minecraft:fishing_rod":9,"minecraft:cobblestone":1035,"minecraft:potion":2,"minecraft:porkchop":4,"minecraft:cooked_porkchop":101,"minecraft:bucket":275,"minecraft:splash_potion":2,"minecraft:birch_stairs":17},"minecraft:killed":{"minecraft:cave_spider":4,"minecraft:witch":3,"minecraft:spider":97,"minecraft:skeleton":138,"minecraft:chicken":104,"minecraft:silverfish":18,"minecraft:magma_cube":43,"minecraft:piglin":8,"minecraft:pig":53,"minecraft:zombie_villager":2,"minecraft:salmon":1,"minecraft:iron_golem":1,"minecraft:creeper":68,"minecraft:sheep":1,"minecraft:pillager":6,"minecraft:zombie":247,"minecraft:blaze":58,"minecraft:cow":197,"minecraft:slime":5,"minecraft:phantom":1,"minecraft:drowned":18,"minecraft:bat":1,"minecraft:wandering_trader":1,"minecraft:hoglin":4,"minecraft:squid":61,"minecraft:wither_skeleton":26,"minecraft:villager":7,"minecraft:enderman":6},"minecraft:dropped":{"minecraft:iron_sword":1,"minecraft:lapis_lazuli":67,"minecraft:glow_ink_sac":4,"minecraft:diamond":28,"minecraft:glass_bottle":1,"minecraft:crafting_table":2,"minecraft:cooked_porkchop":3,"minecraft:warped_fungus_on_a_stick":3,"minecraft:warped_roots":3,"minecraft:saddle":2,"minecraft:rail":14,"minecraft:birch_slab":6,"minecraft:cod":2,"minecraft:flint":16,"minecraft:dirt":132,"minecraft:birch_fence":5,"minecraft:polished_blackstone_brick_stairs":49,"minecraft:wooden_sword":1,"minecraft:gold_nugget":1,"minecraft:writable_book":3,"minecraft:sand":6,"minecraft:iron_pickaxe":1,"minecraft:white_wool":1,"minecraft:bone":33,"minecraft:oak_door":4,"minecraft:gravel":173,"minecraft:blackstone":42,"minecraft:cobbled_deepslate":299,"minecraft:birch_sapling":3,"minecraft:pointed_dripstone":2,"minecraft:rotten_flesh":72,"minecraft:oak_planks":3,"minecraft:salmon":2,"minecraft:trident":1,"minecraft:gunpowder":18,"minecraft:chest":1,"minecraft:spruce_slab":2,"minecraft:basalt":13,"minecraft:birch_button":1,"minecraft:quartz":10,"minecraft:netherrack":1525,"minecraft:egg":234,"minecraft:enchanted_book":1,"minecraft:iron_ingot":3,"minecraft:wheat_seeds":1,"minecraft:minecart":1,"minecraft:iron_helmet":1,"minecraft:golden_axe":1,"minecraft:oak_fence":2,"minecraft:feather":2,"minecraft:cobblestone":1368,"minecraft:granite":103,"minecraft:coal":1,"minecraft:oxeye_daisy":2,"minecraft:diorite":115,"minecraft:ink_sac":3,"minecraft:torch":34,"minecraft:wooden_axe":1,"minecraft:cooked_salmon":1,"minecraft:iron_leggings":2,"minecraft:iron_axe":1,"minecraft:string":31,"minecraft:lily_pad":23,"minecraft:dandelion":1,"minecraft:redstone":217,"minecraft:furnace":1,"minecraft:kelp":3,"minecraft:warped_nylium":3,"minecraft:ender_chest":1,"minecraft:raw_copper":3,"minecraft:tuff":44,"minecraft:chicken":1,"minecraft:iron_boots":1,"minecraft:iron_hoe":1,"minecraft:white_terracotta":1,"minecraft:spruce_fence":1,"minecraft:pumpkin_seeds":4,"minecraft:diamond_sword":2,"minecraft:potato":2,"minecraft:shield":1,"minecraft:diamond_pickaxe":1,"minecraft:andesite":158,"minecraft:birch_sign":2,"minecraft:stone_bricks":2,"minecraft:spider_eye":11,"minecraft:birch_boat":1,"minecraft:bow":4,"minecraft:wooden_pickaxe":1,"minecraft:raw_gold":13,"minecraft:magma_block":1}},"DataVersion":2730}